ddi_fw/datasets/__init__.py
ddi_fw/datasets/core.py
ddi_fw/datasets/dataset_splitter.py
ddi_fw/datasets/db_utils.py
ddi_fw/datasets/processor.py
ddi_fw/datasets/setup_._py
ddi_fw/langchain/__init__.py
ddi_fw/langchain/chroma_storage.py
ddi_fw/langchain/embeddings.py
ddi_fw/langchain/faiss_storage.py
ddi_fw/langchain/sentence_splitter.py
ddi_fw/langchain/storage.py
ddi_fw/langchain/vllm_embeddings.py
ddi_fw/ml/__init__.py
ddi_fw/ml/evaluation_helper.py
ddi_fw/ml/ml_helper.py
ddi_fw/ml/result.py
ddi_fw/ml/tracking_service.py
ddi_fw/ml/ensemble/__init__.py
ddi_fw/ml/ensemble/ensemble_stacking_wrapper.py
ddi_fw/ml/ensemble/ensemble_strategy.py
ddi_fw/ml/ensemble/ensemble_strategy_new.py
ddi_fw/ml/ensemble/ensemble_voting_wrapper.py
ddi_fw/ml/ensemble/ensemble_wrapper.py
ddi_fw/ml/wrappers/__init__.py
ddi_fw/ml/wrappers/catboost_wrapper.py
ddi_fw/ml/wrappers/logistic_regression_wrapper.py
ddi_fw/ml/wrappers/mnb_wrapper.py
ddi_fw/ml/wrappers/model_wrapper.py
ddi_fw/ml/wrappers/pytorch_wrapper.py
ddi_fw/ml/wrappers/random_forest_wrapper.py
ddi_fw/ml/wrappers/tensorflow_wrapper.py
ddi_fw/ml/wrappers/xgboost_wrapper.py
ddi_fw/ner/__init__.py
ddi_fw/ner/mmlrestclient.py
ddi_fw/ner/ner.py
ddi_fw/pipeline/__init__.py
ddi_fw/pipeline/ensemble_pipeline.py
ddi_fw/pipeline/multi_modal_combination_strategy.py
ddi_fw/pipeline/multi_pipeline.py
ddi_fw/pipeline/multi_pipeline_org.py
ddi_fw/pipeline/ner_pipeline.py
ddi_fw/pipeline/pipeline.py
ddi_fw/utils/__init__.py
ddi_fw/utils/categorical_data_encoding_checker.py
ddi_fw/utils/enums.py
ddi_fw/utils/json_helper.py
ddi_fw/utils/kaggle.py
ddi_fw/utils/numpy_utils.py
ddi_fw/utils/package_helper.py
ddi_fw/utils/py7zr_helper.py
ddi_fw/utils/utils.py
ddi_fw/utils/zip_helper.py
ddi_fw/vectorization/__init__.py
ddi_fw/vectorization/feature_vector_generation.py
ddi_fw/vectorization/idf_helper.py
ddi_fw-0.0.298.dist-info/METADATA
ddi_fw-0.0.298.dist-info/WHEEL
ddi_fw-0.0.298.dist-info/top_level.txt
ddi_fw-0.0.298.dist-info/RECORD
