Metadata-Version: 2.4
Name: ddi_fw
Version: 0.0.298
Summary: Do not use :)
Author-email: Kıvanç Bayraktar <bayraktarkivanc@gmail.com>
Maintainer-email: Kıvanç Bayraktar <bayraktarkivanc@gmail.com>
Keywords: Machine Learning
Classifier: Development Status :: 1 - Planning
Classifier: Environment :: Console
Classifier: Intended Audience :: Science/Research
Classifier: Operating System :: OS Independent
Classifier: Framework :: Pytest
Classifier: Framework :: tox
Classifier: Framework :: Sphinx
Classifier: Programming Language :: Python
Classifier: Programming Language :: Python :: 3.10
Classifier: Programming Language :: Python :: 3 :: Only
Classifier: Topic :: Scientific/Engineering :: Artificial Intelligence
Classifier: Topic :: Scientific/Engineering :: Bio-Informatics
Classifier: Topic :: Scientific/Engineering :: Information Analysis
Classifier: Topic :: Scientific/Engineering :: Medical Science Apps.
Requires-Python: >=3.10
Requires-Dist: pydantic<=2.12.4,>=2.11.0
Requires-Dist: tqdm>=4.66.6
Requires-Dist: pandas<=2.3.3,>=2.2.2
Requires-Dist: numpy<=2.3.4,>=1.26.0
Requires-Dist: py7zr==0.22.0
Requires-Dist: xmlschema==3.4.2
Provides-Extra: llm
Requires-Dist: transformers<=4.57.1,>=4.48.0; extra == "llm"
Requires-Dist: tokenizers<=0.22.1,>=0.21.1; extra == "llm"
Requires-Dist: openai>=1.52.2; extra == "llm"
Requires-Dist: langchain<=0.3.27,>=0.3.4; extra == "llm"
Requires-Dist: langchain_community<=0.4.1,>0.3.16; extra == "llm"
Requires-Dist: chromadb<=1.0.4,>=0.7.0; extra == "llm"
Requires-Dist: nltk<=3.9.1,>=3.8.1; extra == "llm"
Requires-Dist: faiss-cpu<1.12.0,>=1.11.0; extra == "llm"
Provides-Extra: ml
Requires-Dist: scikit-learn<=1.6.1,>=1.5.2; extra == "ml"
Requires-Dist: mlflow<=3.2.0,>=2.16.1; extra == "ml"
Requires-Dist: scipy<=1.16.1,>=1.13.1; extra == "ml"
Requires-Dist: plotly==5.24.1; extra == "ml"
Requires-Dist: matplotlib==3.10.0; extra == "ml"
Provides-Extra: ml-tf
Requires-Dist: tensorflow<2.21.0,>=2.17.0; extra == "ml-tf"
Requires-Dist: tf-keras<2.21.0,>=2.17.0; extra == "ml-tf"
Provides-Extra: ml-tf-gpu
Requires-Dist: tensorflow[and-cuda]<2.21.0,>=2.17.0; extra == "ml-tf-gpu"
Requires-Dist: tf-keras<2.21.0,>=2.17.0; extra == "ml-tf-gpu"
Provides-Extra: ml-torch
Requires-Dist: torch>=2.6.0; extra == "ml-torch"
Provides-Extra: no-need
Requires-Dist: sentence-transformers<=5.1.2,>=3.4.1; extra == "no-need"
Requires-Dist: torch>=2.6.0; extra == "no-need"
Provides-Extra: drugbank
Requires-Dist: rdkit==2023.3.3; extra == "drugbank"
Requires-Dist: xmlschema==3.4.2; extra == "drugbank"
Requires-Dist: stanza<=1.10.1,>=1.9.2; extra == "drugbank"
Provides-Extra: utils
Requires-Dist: python-stopwatch==1.1.11; extra == "utils"
Requires-Dist: importlib-resources<=6.5.2,>=6.4.5; extra == "utils"
Requires-Dist: lxml<=5.4.0,>=5.3.0; extra == "utils"
Requires-Dist: pyarrow<=18.1.0,>=18.0.0; extra == "utils"
Requires-Dist: pycryptodomex==3.22.0; extra == "utils"
